{"inkVersion":21,"root":[["^You seem Lonely.","\n","ev","str","^I'll get married","/str","/ev",{"*":"0.c-0","flg":20},"ev","str","^Stop telling me to do things","/str","/ev",{"*":"0.c-1","flg":20},{"c-0":["^ ","end","\n",{"->":"0.g-0"},{"#f":5}],"c-1":["^ ",{"->":"Stop"},"\n",{"->":"0.g-0"},{"#f":5}],"g-0":["done",{"#f":5}]}],"done",{"Stop":[["^Aren't you scared of dying alone?","\n","ev","str","^Yes","/str","/ev",{"*":".^.c-0","flg":20},"ev","str","^I'll do what I want to do.","/str","/ev",{"*":".^.c-1","flg":20},{"c-0":["^ ","end","\n",{"#f":5}],"c-1":["^ ",{"->":"noble"},"\n",{"#f":5}]}],{"#f":1}],"noble":[["^I hope you know there's nothing more noble than to witness and have someone else witness you.","\n","ev","str","^Yes","/str","/ev",{"*":".^.c-0","flg":20},"ev","str","^Shut up","/str","/ev",{"*":".^.c-1","flg":20},{"c-0":["^ ","end","\n",{"#f":5}],"c-1":["end","\n",{"#f":5}]}],{"#f":1}],"#f":1}],"listDefs":{}}